betbot_engine/__init__.py
betbot_engine/engine.py
betbot_engine/parallel_engine.py
betbot_strategies/__init__.py
betbot_strategies/anti_martingale_streak.py
betbot_strategies/base.py
betbot_strategies/classic_martingale.py
betbot_strategies/custom_script.py
betbot_strategies/dalembert.py
betbot_strategies/faucet_cashout.py
betbot_strategies/faucet_grind.py
betbot_strategies/fib_loss_cluster.py
betbot_strategies/fibonacci.py
betbot_strategies/kelly_capped.py
betbot_strategies/labouchere.py
betbot_strategies/max_wager_flow.py
betbot_strategies/one_three_two_six.py
betbot_strategies/oscars_grind.py
betbot_strategies/paroli.py
betbot_strategies/range50_random.py
betbot_strategies/rng_analysis_strategy.py
betbot_strategies/streak_hunter.py
betbot_strategies/target_aware.py
duckdice_api/__init__.py
duckdice_api/api.py
duckdice_api/client.py
duckdice_api/turbo_client.py
duckdice_api/endpoints/__init__.py
duckdice_api/endpoints/history.py
duckdice_api/models/__init__.py
duckdice_api/models/bet.py
duckdice_api/utils/__init__.py
duckdice_api/utils/filters.py
duckdice_api/utils/pagination.py
duckdice_betbot-4.9.2.dist-info/licenses/LICENSE
duckdice_betbot-4.9.2.dist-info/METADATA
duckdice_betbot-4.9.2.dist-info/WHEEL
duckdice_betbot-4.9.2.dist-info/entry_points.txt
duckdice_betbot-4.9.2.dist-info/top_level.txt
duckdice_betbot-4.9.2.dist-info/RECORD
