Metadata-Version: 2.4
Name: duckdice-betbot
Version: 4.9.2
Summary: DuckDice betting bot with 18 strategies, Monte Carlo simulation, and comprehensive CLI
Author-email: Dennis <schnickfitzel1@gmail.com>
License: MIT License
Project-URL: Homepage, https://github.com/sushiomsky/duckdice
Project-URL: Repository, https://github.com/sushiomsky/duckdice
Keywords: duckdice,dice,betting,cli,api,tkinter,strategy
Classifier: Programming Language :: Python :: 3
Classifier: Programming Language :: Python :: 3.9
Classifier: Programming Language :: Python :: 3.10
Classifier: Programming Language :: Python :: 3.11
Classifier: Programming Language :: Python :: 3.12
Classifier: License :: OSI Approved :: MIT License
Classifier: Operating System :: OS Independent
Classifier: Environment :: Console
Classifier: Topic :: Utilities
Requires-Python: >=3.9
License-File: LICENSE
Requires-Dist: requests>=2.31.0
Requires-Dist: PyYAML>=6.0.2
Requires-Dist: rich>=13.7.0
Provides-Extra: gui
Dynamic: license-file
